topsis_python/topsis.py
topsis_ppruthi_101883058-2.0.0.dist-info/LICENSE.txt
topsis_ppruthi_101883058-2.0.0.dist-info/METADATA
topsis_ppruthi_101883058-2.0.0.dist-info/WHEEL
topsis_ppruthi_101883058-2.0.0.dist-info/entry_points.txt
topsis_ppruthi_101883058-2.0.0.dist-info/top_level.txt
topsis_ppruthi_101883058-2.0.0.dist-info/RECORD
